autocorrect_py-2.14.0.dist-info/METADATA
autocorrect_py-2.14.0.dist-info/WHEEL
autocorrect_py.libs/libgcc_s-b5472b99.so.1
autocorrect_py/__init__.py
autocorrect_py/__init__.pyi
autocorrect_py/py.typed
autocorrect_py/autocorrect_py.abi3.so
autocorrect_py-2.14.0.dist-info/RECORD
