Metadata-Version: 2.1
Name: autocorrect-py
Version: 2.14.0
Summary: A linter and formatter for help you improve copywriting, to correct spaces, words, punctuations between CJK (Chinese, Japanese, Korean).
Home-Page: https://github.com/huacnlee/autocorrect
License: MIT
Project-URL: Source Code, https://github.com/huacnlee/autocorrect
